agam_conservation/__init__.py
agam_conservation/cs.py
agam_conservation/data/AgamP4.12.gff3
agam_conservation/data/alignment_depth/2L.depth.tsv
agam_conservation/data/alignment_depth/2R.depth.tsv
agam_conservation/data/alignment_depth/3L.depth.tsv
agam_conservation/data/alignment_depth/3R.depth.tsv
agam_conservation/data/alignment_depth/X.depth.tsv
agam_conservation/data/chr_sizes.txt
agam_conservation/data/phyl_distances.tsv
agam_conservation-0.2.3.dist-info/WHEEL
agam_conservation-0.2.3.dist-info/METADATA
agam_conservation-0.2.3.dist-info/RECORD
