Metadata-Version: 2.1
Name: agam-conservation
Version: 0.2.3
Summary: 
License: MIT
Author: Nace Kranjc
Author-email: nkranjc@ic.ac.uk
Requires-Python: >=3.7,<4.0
Classifier: License :: OSI Approved :: MIT License
Classifier: Programming Language :: Python :: 3
Classifier: Programming Language :: Python :: 3.7
Classifier: Programming Language :: Python :: 3.8
Classifier: Programming Language :: Python :: 3.9
Requires-Dist: h5py
Requires-Dist: humanize
Requires-Dist: numpy
Requires-Dist: pandas
Requires-Dist: requests
Requires-Dist: scikit-allel
Requires-Dist: seaborn
